[
    {
        "timestamp": "2026-03-07T20:48:30.216699",
        "agent": "local_agent",
        "details": {
            "task_id": "4aae2966-504d-4ab6-9b1f-e5422c9bdf2a",
            "action": "email_sent",
            "subject": "Second Email Test",
            "original_file": "email_two.txt"
        }
    },
    {
        "timestamp": "2026-03-07T20:48:30.239240",
        "agent": "local_agent",
        "details": {
            "task_id": "7d6bfd45-8d3f-44aa-aade-ef8e1668c65a",
            "action": "email_sent",
            "subject": "First Email Test",
            "original_file": "email_one.txt"
        }
    },
    {
        "timestamp": "2026-03-07T20:48:30.268964",
        "agent": "local_agent",
        "details": {
            "task_id": "ec5b78e3-a9b5-4dc9-8a28-765872979dcb",
            "action": "email_sent",
            "subject": "Project Update Request",
            "original_file": "project_update.txt"
        }
    }
]